setup.py
django_skd_tools.egg-info/PKG-INFO
django_skd_tools.egg-info/SOURCES.txt
django_skd_tools.egg-info/dependency_links.txt
django_skd_tools.egg-info/requires.txt
django_skd_tools.egg-info/top_level.txt
skd_tools/__init__.py
skd_tools/decorators.py
skd_tools/fields.py
skd_tools/mixins.py
skd_tools/utils.py