Metadata-Version: 1.1
Name: django-skd-tools
Version: 0.2.1
Summary: Steelkiwi Django Tools
Home-page: https://github.com/steelkiwi/django-skd-tools
Author: Steelkiwi
Author-email: vilisov@steelkiwi.com
License: MIT
Keywords: django tools helpers
Platform: UNKNOWN
Classifier: Environment :: Web Environment
Classifier: Intended Audience :: Developers
Classifier: License :: OSI Approved :: MIT License
Classifier: Operating System :: OS Independent
Classifier: Programming Language :: Python
Classifier: Topic :: Internet :: WWW/HTTP :: Dynamic Content
Classifier: Topic :: Software Development :: Libraries :: Python Modules
